<?xml version="1.0" encoding="utf-8"?>
<modification>
	<name>R.Gen OpenCart Themes</name>
	<version>4.20</version>
	<author>R_GENESIS</author>
	<link>http://themeforest.net/user/R_GENESIS/portfolio</link>
	
	<file path="system/engine/front.php">
		<operation>
			<search><![CDATA[foreach ($this->pre_action as $pre_action) {]]></search>
			<add position="replace"><![CDATA[
			/* rgen changes */
		foreach ($this->pre_action as $i => $pre_action) {
			//-------------------
			]]></add>
		</operation>
		<operation>
			<search><![CDATA[$result = $this->execute($pre_action);]]></search>
			<add position="after"><![CDATA[
			/* rgen changes */
			if ($i == 0) {
				$configData = $this->registry->get('config');
				if (isset($configData)) {
					if($this->registry->get('config')->get('theme_default_directory') == 'rgen-opencart'){
						include(DIR_SYSTEM . 'rgen/startup.php');
					}
				}
			}
			//-------------------
			]]></add>
		</operation>
	</file>

	<file path="system/engine/loader.php">
		<operation>
			<search><![CDATA[public function language($route) {]]></search>
			<add position="before"><![CDATA[
			/* rgen changes */
			public function rgen($key) { 
				if($this->registry->get('config')->get('theme_default_directory') == 'rgen-opencart'){
					if ($this->registry->get('rgen_check') === false) {
						echo $this->registry->get('rgen_error');
						exit();
					} else {
						return $this->registry->get('rgen')->{$key}; 
					}
				}
			}
			//-------------------
			]]></add>
		</operation>
	</file>

	<file path="system/library/template/basic.php">
		<operation>
			<search><![CDATA[public function set($key, $value) {]]></search>
			<add position="before"><![CDATA[
			/* rgen changes */
			public function rgen($key) { 
				global $registry;
				if($registry->get('config')->get('theme_default_directory') == 'rgen-opencart'){
					if ($registry->get('rgen_check') === false) {
						echo $registry->get('rgen_error');
						exit();
					} else {
						return $registry->get('rgen')->{$key}; 
					}
				}
			}

			public function __get($key) {
		        global $registry;
		        return $registry->get($key);
		    }

		    public function __set($key, $value) {
		        global $registry;
		        $registry->set($key, $value);
		    }
			//-------------------
			]]></add>
		</operation>
	</file>

	<file path="catalog/model/tool/image.php">
		<operation>
			<search><![CDATA[public function resize($filename, $width, $height) {]]></search>
			<add position="replace"><![CDATA[
			/* rgen changes */
			public function resize($filename, $width, $height, $resize_type = '') {
			//-------------------
			]]></add>
		</operation>
		<operation>
			<search><![CDATA[$image->resize($width, $height);]]></search>
			<add position="replace"><![CDATA[
			/* rgen changes */
			$image->resize($width, $height, $resize_type);
			//-------------------
			]]></add>
		</operation>
	</file>

	<file path="admin/model/design/layout.php">
		<operation>
			<search index="0"><![CDATA[$this->db->query("DELETE FROM " . DB_PREFIX . "layout_module WHERE layout_id = '" . (int)$layout_id . "'");]]></search>
			<add position="replace"><![CDATA[$this->db->query("DELETE FROM " . DB_PREFIX . "layout_module WHERE layout_id = '" . (int)$layout_id . "' AND `code` NOT LIKE 'rgen_%'");]]></add>
		</operation>
		<operation>	
			<search><![CDATA[$query = $this->db->query("SELECT * FROM " . DB_PREFIX . "layout_module WHERE layout_id = '" . (int)$layout_id . "' ORDER BY position ASC, sort_order ASC");]]></search>
			<add position="replace"><![CDATA[$query = $this->db->query("SELECT * FROM " . DB_PREFIX . "layout_module WHERE layout_id = '" . (int)$layout_id . "' AND `code` NOT LIKE 'rgen_%' ORDER BY position ASC, sort_order ASC");]]></add>
		</operation>
	</file>
	<file path="admin/model/extension/module.php">
		<operation>
			<search><![CDATA[$this->db->query("DELETE FROM `" . DB_PREFIX . "layout_module` WHERE `code` LIKE '%." . (int)$module_id . "'");]]></search>
			<add position="replace"><![CDATA[$this->db->query("DELETE FROM `" . DB_PREFIX . "layout_module` WHERE `code` LIKE '%." . (int)$module_id . "' AND `code` NOT LIKE 'rgen_%'");]]></add>
		</operation>
		<operation>
			<search><![CDATA[$this->db->query("DELETE FROM `" . DB_PREFIX . "layout_module` WHERE `code` LIKE '" . $this->db->escape($code . '.%') . "'");]]></search>
			<add position="replace"><![CDATA[$this->db->query("DELETE FROM `" . DB_PREFIX . "layout_module` WHERE `code` LIKE '" . $this->db->escape($code . '.%') . "' AND `code` NOT LIKE 'rgen_%'");]]></add>
		</operation>
	</file>
	
	<file path="catalog/controller/common/column_left.php">
		<operation>
			<search><![CDATA[foreach ($modules as $module) {]]></search>
			<add position="before"><![CDATA[
				/* rgen changes */
				if($this->registry->get('config')->get('theme_default_directory') == 'rgen-opencart'){
					$data['current_position'] = 'column_left';
					$modules = array_merge($modules, $this->model_design_layout->getLayoutModules(9999, 'column_left'));
				}
				//-------------------
			]]></add>
		</operation>
		<operation>
			<search><![CDATA[$part = explode('.', $module['code']);]]></search>
			<add position="after"><![CDATA[
				/* rgen changes */
				if($this->registry->get('config')->get('theme_default_directory') == 'rgen-opencart' && $this->registry->get('rgen_check') != false){
					$rgen = explode('_', $part[0]);
					if (isset($rgen) && sizeof($rgen) > 0) {
						if ($rgen[0] == 'rgen' && isset($part[2])) {
							if (isset($part[0]) && $this->config->get($part[0] . '_R.' . $part[1] . '.' . $part[2])) {
								$setting_info = $module['code'];
								$data['modules'][] = $this->load->controller('rgen/' . $rgen[1], $setting_info);
							}
						}
					}
					
					if (isset($part[0])) {
						$tmp[] = $part[0];
						$this->rgen->rgenSettings->setSettings($module['position'], $tmp);
						$this->rgen->rgenSettings->setSettings('current_pos', $module['position']);
					}
				}
				//-------------------
			]]></add>
		</operation>
	</file>
	<file path="catalog/controller/common/column_right.php">
		<operation>
			<search><![CDATA[foreach ($modules as $module) {]]></search>
			<add position="before"><![CDATA[
				/* rgen changes */
				if($this->registry->get('config')->get('theme_default_directory') == 'rgen-opencart'){
					$data['current_position'] = 'column_right';
					$modules = array_merge($modules, $this->model_design_layout->getLayoutModules(9999, 'column_right'));
				}
				//-------------------
			]]></add>
		</operation>
		<operation>
			<search><![CDATA[$part = explode('.', $module['code']);]]></search>
			<add position="after"><![CDATA[
				/* rgen changes */
				if($this->registry->get('config')->get('theme_default_directory') == 'rgen-opencart' && $this->registry->get('rgen_check') != false){
					$rgen = explode('_', $part[0]);
					if (isset($rgen) && sizeof($rgen) > 0) {
						if ($rgen[0] == 'rgen' && isset($part[2])) {
							if (isset($part[0]) && $this->config->get($part[0] . '_R.' . $part[1] . '.' . $part[2])) {
								$setting_info = $module['code'];
								$data['modules'][] = $this->load->controller('rgen/' . $rgen[1], $setting_info);
							}
						}
					}
					
					if (isset($part[0])) {
						$tmp[] = $part[0];
						$this->rgen->rgenSettings->setSettings($module['position'], $tmp);
						$this->rgen->rgenSettings->setSettings('current_pos', $module['position']);
					}
				}
				//-------------------
			]]></add>
		</operation>
	</file>
	<file path="catalog/controller/common/content_bottom.php">
		<operation>
			<search><![CDATA[foreach ($modules as $module) {]]></search>
			<add position="before"><![CDATA[
				/* rgen changes */
				if($this->registry->get('config')->get('theme_default_directory') == 'rgen-opencart'){
					$data['current_position'] = 'content_bottom';
					$modules = array_merge($modules, $this->model_design_layout->getLayoutModules(9999, 'content_bottom'));
				}
				//-------------------
			]]></add>
		</operation>
		<operation>
			<search><![CDATA[$part = explode('.', $module['code']);]]></search>
			<add position="after"><![CDATA[
				/* rgen changes */
				if($this->registry->get('config')->get('theme_default_directory') == 'rgen-opencart' && $this->registry->get('rgen_check') != false){
					$rgen = explode('_', $part[0]);
					if (isset($rgen) && sizeof($rgen) > 0) {
						if ($rgen[0] == 'rgen' && isset($part[2])) {
							if (isset($part[0]) && $this->config->get($part[0] . '_R.' . $part[1] . '.' . $part[2])) {
								$setting_info = $module['code'];
								$data['modules'][] = $this->load->controller('rgen/' . $rgen[1], $setting_info);
							}
						}
					}
					
					if (isset($part[0])) {
						$tmp[] = $part[0];
						$this->rgen->rgenSettings->setSettings($module['position'], $tmp);
						$this->rgen->rgenSettings->setSettings('current_pos', $module['position']);
					}
				}
				//-------------------
			]]></add>
		</operation>
	</file>
	<file path="catalog/controller/common/content_top.php">
		<operation>
			<search><![CDATA[foreach ($modules as $module) {]]></search>
			<add position="before"><![CDATA[
			/* rgen changes */
			if($this->registry->get('config')->get('theme_default_directory') == 'rgen-opencart'){
				$data['current_position'] = 'content_top';
				$modules = array_merge($modules, $this->model_design_layout->getLayoutModules(9999, 'content_top'));
			}
			//-------------------
			]]></add>
		</operation>
		<operation>
			<search><![CDATA[$part = explode('.', $module['code']);]]></search>
			<add position="after"><![CDATA[
				/* rgen changes */
				if($this->registry->get('config')->get('theme_default_directory') == 'rgen-opencart' && $this->registry->get('rgen_check') != false){
					$rgen = explode('_', $part[0]);
					if (isset($rgen) && sizeof($rgen) > 0) {
						if ($rgen[0] == 'rgen' && isset($part[2])) {
							if (isset($part[0]) && $this->config->get($part[0] . '_R.' . $part[1] . '.' . $part[2])) {
								$setting_info = $module['code'];
								$data['modules'][] = $this->load->controller('rgen/' . $rgen[1], $setting_info);
							}
						}
					}
					
					if (isset($part[0])) {
						$tmp[] = $part[0];
						$this->rgen->rgenSettings->setSettings($module['position'], $tmp);
						$this->rgen->rgenSettings->setSettings('current_pos', $module['position']);
					}
				}
				//-------------------
			]]></add>
		</operation>
	</file>

	<file path="catalog/controller/common/header.php">
		<operation>
			<search><![CDATA[$data['cart'] = $this->load->controller('common/cart');]]></search>
			<add position="after"><![CDATA[
			/* rgen changes */
			$rgen_positions = array(
				'main_menu'  => 'main_menu',
				'pos_ss'     => 'slideshow',

				'top_upper'  => 'top_upper',
				'top_left'   => 'top_left',
				'top_middle' => 'top_middle',
				'top_right'  => 'top_right',
				'top_lower'  => 'top_lower'
			);

			$this->user = new Cart\User($this->registry);
			
			if(!$this->config->get('config_maintenance') || $this->user->isLogged()){
				if($this->registry->get('config')->get('theme_default_directory') == 'rgen-opencart' && $this->registry->get('rgen_check') != false){
					foreach ($rgen_positions as $key => $value) {
						$data[$key] = $this->load->controller('common/rgenpositions/'.$value);
					}
				}
			}else{
				if($this->registry->get('config')->get('theme_default_directory') == 'rgen-opencart' && $this->registry->get('rgen_check') != false){
					foreach ($rgen_positions as $key => $value) {
						$data[$key] = '';
					}
				}
			}
			$this->load->controller('rgen/assets');
			//-------------------
			]]></add>
		</operation>
	</file>
	<file path="catalog/controller/common/footer.php">
		<operation>
			<search><![CDATA[$data['powered'] = sprintf($this->language->get('text_powered'), $this->config->get('config_name'), date('Y', time()));]]></search>
			<add position="after"><![CDATA[
			/* rgen changes */
			$rgen_positions = array(
				'bottom_upper'  => 'bottom_upper',
				'bottom_left'   => 'bottom_left',
				'bottom_middle' => 'bottom_middle',
				'bottom_right'  => 'bottom_right',
				'bottom_lower'  => 'bottom_lower',
				'stickydata'    => 'stickydata'
			);

			$this->user = new Cart\User($this->registry);

			if(!$this->config->get('config_maintenance') || $this->user->isLogged()){
				if($this->registry->get('config')->get('theme_default_directory') == 'rgen-opencart' && $this->registry->get('rgen_check') != false){
					foreach ($rgen_positions as $key => $value) {
						$data[$key] = $this->load->controller('common/rgenpositions/'.$value);
					}
				}
			}else{
				if($this->registry->get('config')->get('theme_default_directory') == 'rgen-opencart' && $this->registry->get('rgen_check') != false){
					foreach ($rgen_positions as $key => $value) {
						$data[$key] = '';
					}
				}
			}
			//-------------------
			]]></add>
		</operation>
	</file>


	<file path="catalog/controller/module/{featured,bestseller,latest,special,slideshow}*.php">
		<operation>
			<search><![CDATA[public function index($setting) {]]></search>
			<add position="after"><![CDATA[$data['settings'] = $setting;]]></add>
		</operation>
	</file>
	<file path="catalog/controller/module/{bestseller,latest,special}*.php">
		<operation>
			<search><![CDATA['rating'      => $rating,]]></search>
			<add position="before"><![CDATA[
				'quantity'    => $result['quantity'],
				'stock_status'=> $result['stock_status'],
			]]></add>
		</operation>
	</file>
	<file path="catalog/controller/module/featured.php">
		<operation>
			<search><![CDATA['rating'      => $rating,]]></search>
			<add position="before"><![CDATA[
				'quantity'    => $product_info['quantity'],
				'stock_status'=> $product_info['stock_status'],
			]]></add>
		</operation>
	</file>
	<file path="catalog/controller/product/category.php">
		<operation>
			<search><![CDATA['href' => $this->url->link('product/category', 'path=' . $this->request->get['path'] . '_' . $result['category_id'] . $url)]]></search>
			<add position="before"><![CDATA['pic' => $this->model_tool_image->resize($result['image'] ? $result['image'] : 'no_image.jpg', $this->config->get($this->config->get('config_theme') . '_image_category_width'), $this->config->get($this->config->get('config_theme') . '_image_category_height')),]]></add>
		</operation>
		<operation>
			<search><![CDATA['minimum'     => $result['minimum'] > 0 ? $result['minimum'] : 1,]]></search>
			<add position="before"><![CDATA[
				'quantity'    => $result['quantity'],
				'stock_status'=> $result['stock_status'],
			]]></add>
		</operation>
	</file>
	<file path="catalog/controller/module/category.php">
		<operation>
			<search><![CDATA[if ($category['category_id'] == $data['category_id']) {]]></search>
			<add position="replace"><![CDATA[if ($category['category_id']) {]]></add>
		</operation>
	</file>
	<file path="catalog/controller/product/product.php">
		<operation>
			<search><![CDATA[$data['description'] = html_entity_decode($product_info['description'], ENT_QUOTES, 'UTF-8');]]></search>
			<add position="after"><![CDATA[$data['prd_quantity'] = $product_info['quantity'];]]></add>
		</operation>
	</file>

</modification>